roadsync_slogger/__init__.py
roadsync_slogger/logger.py
roadsync_slogger-1.2.2.dist-info/METADATA
roadsync_slogger-1.2.2.dist-info/WHEEL
roadsync_slogger-1.2.2.dist-info/RECORD
