Metadata-Version: 2.1
Name: roadsync_slogger
Version: 1.2.2
Summary: A python logger similar to Go's slogger
License: MIT
Author: SRE
Author-email: sre@roadsync.com
Requires-Python: >=3.9,<4.0
Classifier: License :: OSI Approved :: MIT License
Classifier: Programming Language :: Python :: 3
Classifier: Programming Language :: Python :: 3.9
Classifier: Programming Language :: Python :: 3.10
Classifier: Programming Language :: Python :: 3.11
Classifier: Programming Language :: Python :: 3.12
Requires-Dist: orjson (>=3.10.7,<4.0.0)
